<annotation>
	<folder>images</folder>
	<filename>investor.vanguard.com_77.png</filename>
	<path>D:\Github\web-court\dataset\images\investor.vanguard.com_77.png</path>
	<source>
		<database>Unknown</database>
	</source>
	<size>
		<width>3841</width>
		<height>1821</height>
		<depth>3</depth>
	</size>
	<segmented>0</segmented>
	<object>
		<name>login_form</name>
		<pose>Unspecified</pose>
		<truncated>0</truncated>
		<difficult>0</difficult>
		<bndbox>
			<xmin>430</xmin>
			<ymin>335</ymin>
			<xmax>2638</xmax>
			<ymax>579</ymax>
		</bndbox>
	</object>
	<object>
		<name>login_button</name>
		<pose>Unspecified</pose>
		<truncated>0</truncated>
		<difficult>0</difficult>
		<bndbox>
			<xmin>1928</xmin>
			<ymin>399</ymin>
			<xmax>2617</xmax>
			<ymax>544</ymax>
		</bndbox>
	</object>
</annotation>
